{"submission_id": "4661zi", "submission_title": "My setup at my old apt vs my new apt. (more info in comments)", "submission_url": "/r/Workspaces/comments/4661zi/my_setup_at_my_old_apt_vs_my_new_apt_more_info_in/", "submission_img_url": "http://imgur.com/a/5lKup", "submission_author_name": "Erickster", "submission_author_id": "98iqb", "submission_author_subreddits": ["movies", "Dermatology", "oddlysatisfying", "HumansBeingBros", "mildlyinteresting", "UNBGBBIIVCHIDCTIICBG", "northcounty", "mexico", "Ska", "alcoholism", "f150", "battlestations", "assholedesign", "longbeach", "subredditcancer", "NewOrleans", "SCREENPRINTING", "reactiongifs", "gaming", "tifu", "jobs", "sex", "Fitness", "sandiego", "Music", "likeus", "hometheater", "AnimalsBeingConfused", "thisismylifenow", "pics", "SanDiegoSurfFishing", "podcast", "business", "tmobile", "AccidentalRenaissance", "audioengineering", "Workspaces", "babyelephantgifs", "wallstreetbets", "AdviceAnimals", "landscaping", "samthecookingguy", "insanepeoplefacebook", "Killtony", "virtualreality", "legal", "IAmA", "FoodSanDiego", "Eyebleach", "calvinandhobbes", "SEO", "CozyPlaces", "Cooking", "smallbusiness", "animation", "Divorce", "aww", "gifs", "lastimages", "Showerthoughts", "millionairemakers", "totallynotrobots", "WTF", "resumes", "Animals", "interestingasfuck", "humor", "NatureIsFuckingLit", "civic", "wholesomegifs", "DIY", "GalaxyNote9", "fitnesscirclejerk", "lego", "estoration", "WastedGifs", "wheredidthesodago", "atheism", "AskTechnology", "worldnews", "Resume", "ShadowPC", "insects", "Ghosts", "Art", "chromeos", "healthcare", "Unexpected", "Anaheim", "BeerSanDiego", "escondido", "Iowa", "trees", "disneyvacation", "BeAmazed", "AskDocs", "vidme", "AskMen", "videos", "youdontsurf", "travel", "AskReddit", "podcasts", "mildlyinfuriating", "Poway", "news", "nonononoyes", "AnimalsBeingJerks", "UpliftingNews", "drunk", "woahdude", "doggifs", "cancer", "OutOfTheLoop", "HomeDecorating", "AnimalsBeingBros", "therewasanattempt", "colorizationrequests", "food", "todayilearned", "funny", "conspiracy", "FoodPorn"]}