{"submission_id": "4jctfl", "submission_title": "Desk Design Idea! Feedback? Ideas? Help? All appreciated.", "submission_url": "/r/Workspaces/comments/4jctfl/desk_design_idea_feedback_ideas_help_all/", "submission_img_url": "http://imgur.com/zed82ek", "submission_author_name": "JoshWalkerMedia", "submission_author_id": "jlalj", "submission_author_subreddits": ["summonerschool", "Nike", "arkmodding", "PickAnAndroidForMe", "MinecraftBuddies", "Channelart", "forhire", "Smite", "videos", "warcraftlore", "Fantasy", "IKEA", "hearthstone", "skyrimmods", "leagueoflegends", "shannara", "podcasts", "steelseries", "NoMansSkyTheGame", "wow", "mac", "GlobalOffensive", "FaZeCLAN", "feedthebeastservers", "freelance", "Games", "DigitalPainting", "Smartphones", "gaming", "RedReserve", "Minecraft", "Art", "postprocessing", "immortals_gg", "DesignJobs", "VoiceActing", "feedthebeast", "fo4", "NoContract", "photoshop", "gameDevClassifieds", "Cinema4D", "pcmasterrace", "graphic_design", "twitchstreams", "paragon", "ImaginaryFallout", "MechanicalKeyboards", "ElderScrolls", "DnD", "GlobalOffensiveTrade", "electronic_cigarette", "u_JoshWalkerMedia", "Workspaces", "Twitter", "razer", "photography", "computers", "MODELING"]}