{"submission_id": "4khgmo", "submission_title": "My small studio apartment workspace.", "submission_url": "/r/Workspaces/comments/4khgmo/my_small_studio_apartment_workspace/", "submission_img_url": "http://imgur.com/a/hG1IQ", "submission_author_name": "jayb33c33", "submission_author_id": "e1eef", "submission_author_subreddits": ["trees", "magicTCG", "iPhoneSE", "Paleo", "ElectricUnicycle", "SanJoseSharks", "videos", "disney", "AE86", "sanfrancisco", "vaporents", "doctorwho", "short", "iphone", "mac", "declutter", "corgi", "pokemongoSF", "headphones", "hockeyjerseys", "SoylentMarket", "onewheel", "gopro", "EDC", "gaming", "boostedboards", "running", "VeteransBenefits", "AskSF", "cosplay", "ENGLISH", "postmates", "motorcycles", "discgolf", "apple", "legaladvice", "amazonecho", "Costco", "Sneakers", "supremeclothing", "snowboarding", "AMCsAList", "Workspaces", "SFGiants", "stockx", "PokemonLetsGo", "NintendoSwitch"]}