{"submission_id": "6reui3", "submission_title": "Tinker station built on top of my dogs cage. He doesn't stay in there anymore so thinking about maybe adding some shelving under there. Any ideas are appreciated", "submission_url": "/r/workstations/comments/6reui3/tinker_station_built_on_top_of_my_dogs_cage_he/", "submission_img_url": "https://i.redd.it/6k7k30fbskdz.jpg", "submission_author_name": "jsometimes", "submission_author_id": "138h86", "submission_author_subreddits": ["workstations", "setups", "coupons", "AskReddit"]}