{"submission_id": "90tmym", "submission_title": "I couldn't find a desk that suited my setup, so me and the old man spent some quality time together and built one from all reclaimed materials. Love you dad!", "submission_url": "/r/battlestations/comments/90tmym/i_couldnt_find_a_desk_that_suited_my_setup_so_me/", "submission_img_url": "https://imgur.com/0uq5m0A", "submission_author_name": "zakh134", "submission_author_id": "5ddsc", "submission_author_subreddits": ["movies", "classicwow", "oddlysatisfying", "pcgaming", "StarWars", "whitepeoplegifs", "clevercomebacks", "shorthairedhotties", "Bad_Cop_No_Donut", "HumansBeingBros", "zelda", "godtiersuperpowers", "garlicoin", "Futurology", "2healthbars", "Cuckold", "brooklynninenine", "teenagers", "ThatLookedExpensive", "thanosdidnothingwrong", "mildlyinteresting", "UNBGBBIIVCHIDCTIICBG", "Fuckthealtright", "standupshots", "IdiotsInCars", "pcmods", "FloridaMan", "skyrim", "WritingPrompts", "theydidthemath", "Breath_of_the_Wild", "chemicalreactiongifs", "imsorryjon", "battlestations", "HistoryPorn", "corgi", "Perfectfit", "ENLIGHTENEDCENTRISM", "maybemaybemaybe", "gadgets", "DadReflexes", "quityourbullshit", "Android", "BetterEveryLoop", "tifu", "reactiongifs", "gaming", "BikiniBottomTwitter", "youseeingthisshit", "LateStageCapitalism", "FuckingWithNature", "politics", "SweatyPalms", "fffffffuuuuuuuuuuuu", "2meirl4meirl", "confession", "forbiddensnacks", "ihadastroke", "Vive", "smoobypost", "BrandNewSentence", "absolutelynotme_irl", "outside", "NSFWFunny", "BeansInThings", "PeopleFuckingDying", "HistoryMemes", "ChoosingBeggars", "SoundsLikeMusic", "PublicFreakout", "greentext", "thisismylifenow", "webcomics", "creepy", "pics", "Birbs", "iamverybadass", "awfuleverything", "bloodborne", "GirlsMirin", "nottheonion", "AccidentalRenaissance", "MaliciousCompliance", "blackmagicfuckery", "sadcringe", "ProgrammerHumor", "WTFgaragesale", "AdviceAnimals", "darksouls", "Cyberpunk", "insanepeoplefacebook", "blackpeoplegifs", "ZeroWaste", "facepalm", "EliteDangerous", "beetlejuicing", "buildapc", "oldpeoplefacebook", "EngineeringPorn", "MurderedByWords", "h3h3productions", "JusticeServed", "nextfuckinglevel", "DiWHY", "StrangerThings", "ImaginarySliceOfLife", "PlayItAgainSam", "4chan", "woooosh", "rareinsults", "INEEEEDIT", "marvelstudios", "harrypotter", "natureismetal", "TheBigLezShow", "fightporn", "playrust", "Eyebleach", "CozyPlaces", "toofers", "suicidebywords", "BoneAppleTea", "coolguides", "AmItheAsshole", "tumblr", "SwordsComic", "medizzy", "memes", "PUBATTLEGROUNDS", "DarkSouls2", "wholesomebpt", "badassvideos", "aww", "gifs", "holdmyjuicebox", "continuityporn", "HadToHurt", "whatisthisthing", "cursedcomments", "OnePiece", "DnD", "dankmemes", "Showerthoughts", "technology", "Rainbow6", "OldSchoolCool", "Instagramreality", "Frugal", "BlackPeopleTwitter", "WTF", "Bossfight", "interestingasfuck", "PokemonGo_MInnesota", "southpark", "nba", "KidsAreFuckingStupid", "confusing_perspective", "HongKong", "ChildrenFallingOver", "NatureIsFuckingLit", "freefolk", "UnethicalLifeProTips", "Cringetopia", "bettafish", "holdmyfeedingtube", "youtubehaiku", "softwaregore", "DIY", "insaneparents", "perfectlycutscreams", "technicallythetruth", "lego", "marvelmemes", "see", "mechanical_gifs", "curvy", "surrealmemes", "baseball", "educationalgifs", "FunnyandSad", "sixwordstories", "cringepics", "DeepFriedMemes", "gamegrumps", "CrappyDesign", "hmmm", "holdmyredbull", "holdmycosmo", "CatastrophicFailure", "WatchPeopleDieInside", "catpranks", "worldnews", "ThatsInsane", "PoliticalHumor", "ich_iel", "ShittyLifeProTips", "MyPeopleNeedMe", "Whatcouldgowrong", "PrequelMemes", "Morrowind", "Minecraft", "instant_regret", "instantkarma", "Offensive_Wallpapers", "fantanoforever", "explainlikeimfive", "noita", "Undertale", "ATBGE", "meirl", "4PanelCringe", "MoundofVenus", "comics", "DesignPorn", "apple", "guns", "pcmasterrace", "MovieDetails", "comedyheaven", "polandball", "Unexpected", "Neverbrokeabone", "Awwducational", "BuyItForLife", "smashbros", "anime_irl", "science", "pussypassdenied", "WhyWereTheyFilming", "MapPorn", "LivestreamFail", "Damnthatsinteresting", "unpopularopinion", "holdmybeer", "DCcomics", "PewdiepieSubmissions", "NintendoSwitch", "nononono", "dumbasseswithlighters", "trees", "NuclearThrone", "trashy", "MensRights", "WhitePeopleTwitter", "BeAmazed", "SmashBrosUltimate", "videos", "FilthyFrank", "dbz", "FiftyFifty", "space", "CasualUK", "nostalgia", "AskReddit", "me_irl", "FellowKids", "news", "starterpacks", "mildlyinfuriating", "nonononoyes", "Mordhau", "AnimalsBeingJerks", "justneckbeardthings", "UpliftingNews", "niceguys", "cursedimages", "Dashcam", "woahdude", "Wellthatsucks", "DnDGreentext", "techsupportgore", "pokemon", "Fallout", "RoastMe", "thalassophobia", "ShitPostCrusaders", "aviation", "IDontWorkHereLady", "GoCommitDie", "AbsoluteUnits", "shittyfoodporn", "dndmemes", "photoshopbattles", "nevertellmetheodds", "HydroHomies", "AnimalsBeingBros", "playrustart", "therewasanattempt", "ironscape", "MemeEconomy", "ContagiousLaughter", "apexlegends", "ActLikeYouBelong", "todayilearned", "halo", "MakeMeSuffer", "madlads", "blursedimages", "StardewValley", "MadeMeSmile", "specializedtools", "SubredditDrama", "gatekeeping", "wholesomememes", "funny", "NegativeWithGold", "Overwatch", "StoppedWorking", "MMA", "ScottishPeopleTwitter", "2007scape", "woodworking"]}