{"submission_id": "90yslw", "submission_title": "GTSpeedster's Sim Racing Battlestation", "submission_url": "/r/battlestations/comments/90yslw/gtspeedsters_sim_racing_battlestation/", "submission_img_url": "https://i.redd.it/jpbzosqzwib11.jpg", "submission_author_name": "GTSpeedster", "submission_author_id": "rs9jj", "submission_author_subreddits": ["AUTOMOBILISTA", "movies", "mancave", "wec", "DIY", "simracing", "gamingpc", "mildlyinteresting", "AskReddit", "news", "marvelstudios", "masseffect", "battlestations", "F1Game", "worldnews", "television", "ABCDesis", "gaming", "politics", "iRacing", "explainlikeimfive", "gifs", "todayilearned", "civ", "rFactor", "pcmasterrace", "sciencefiction", "pics", "science", "Showerthoughts", "funny", "LifeProTips", "Jokes", "brasil"]}