{"submission_id": "bi87qb", "submission_title": "My Studio 2019 v2", "submission_url": "/r/Workspaces/comments/bi87qb/my_studio_2019_v2/", "submission_img_url": "https://i.redd.it/njmq9lsk2yu21.jpg", "submission_author_name": "Reg3e", "submission_author_id": "118ij6", "submission_author_subreddits": ["movies", "fireemblem", "discordapp", "TheSilphRoad", "Futurology", "CircleofTrust", "LogitechG", "casualnintendo", "drawing", "space", "pokemongo", "AskReddit", "manga", "ImaginarySliceOfLife", "lilypichu", "SonicTheHedgehog", "starcitizen", "pokemon", "DigitalArt", "Dofus", "battlestations", "ClipStudio", "mechanicalpencils", "gadgets", "worldnews", "grandorder", "untitledgoosegame", "microsoft", "manken", "gaming", "Steam", "animation", "VirtualYoutubers", "Minecraft", "KizunaAI", "eGPU", "Windows10", "anime", "comics", "Paladins", "CohhCarnage", "pcmasterrace", "FireEmblemThreeHouses", "thinkpad", "science", "Surface", "Damnthatsinteresting", "StarVStheForcesofEvil", "razer", "Workspaces", "wacom", "wakfu", "wholesomeanimemes"]}