{"submission_id": "c92j7e", "submission_title": "Orange?", "submission_url": "/r/battlestations/comments/c92j7e/orange/", "submission_img_url": "https://i.redd.it/daagz70ffa831.jpg", "submission_author_name": "majeu", "submission_author_id": "bskxawd", "submission_author_subreddits": ["nvidia", "pcmasterrace", "MINI", "Vape_Porn", "MadeMeSmile", "VapePorn", "Coilporn", "whatsthisbug", "woahdude", "battlestations", "RocketLeague", "Vaping", "RocketLeagueFriends", "interestingasfuck", "ForzaAuctions"]}