{"submission_id": "dqqos9", "submission_title": "Thoughts on IKEA office chairs?", "submission_url": "/r/Workspaces/comments/dqqos9/thoughts_on_ikea_office_chairs/", "submission_img_url": "https://www.reddit.com/r/Workspaces/comments/dqqos9/thoughts_on_ikea_office_chairs/", "submission_author_name": "Mathcmput", "submission_author_id": "14wxje", "submission_author_subreddits": ["mentalhealth", "verizon", "fragrance", "PersonalFinanceCanada", "AcademicPsychology", "UPS", "AsianMasculinity", "CircleofTrust", "canada", "mildlyinteresting", "Monitors", "spectrex360", "ManyBaggers", "galaxys10", "gadgets", "Edmonton", "bapcsalescanada", "Android", "jobs", "chanceme", "Coffee", "applemaps", "depressionregimens", "Music", "AppleMusic", "DMV", "iamverybadass", "VideoGameDealsCanada", "uAlberta", "Sneakers", "tmobile", "backpacks", "audioengineering", "Workspaces", "Advice", "contacts", "tretinoin", "Allergies", "iPhone11ProMax", "Shoes", "GalaxyS8", "AndroidQuestions", "buildapc", "IKEA", "optometry", "laptops", "depression", "careerguidance", "Lighting", "homemaking", "IAmA", "KoodoReferrals", "AskPsychiatry", "Fjallraven", "Dell", "HomeImprovement", "venturacounty", "Hewlett_Packard", "MakeupAddiction", "NoContract", "iPhoneXsMax", "legaladvice", "TalesFromRetail", "fixit", "Showerthoughts", "Surface", "Tinder", "spotify", "Frugal", "frontierfios", "Outdoors", "ADHD", "UCalgary", "OCD", "pens", "hardwareswap", "ApplyingToCollege", "LOONA", "macbook", "California", "antidepressants", "iphone", "tressless", "walmart", "lgv30", "SneakersCanada", "SkincareAddiction", "Lenovo", "iphonehelp", "iPhone11Pro", "headphones", "schizophrenia", "HeadphoneAdvice", "worldnews", "lastfm", "AnimalCrossing", "explainlikeimfive", "GooglePixel", "AskNYC", "SuggestALaptop", "techsupport", "apple", "ATT", "thinkpad", "BuyItForLife", "pharmacy", "iOSBeta", "asianamerican", "AusSkincare", "LifeProTips", "Rogers", "malefashionadvice", "unpopularopinion", "NintendoSwitch", "PickAnAndroidForMe", "ShadowBan", "onebag", "iPhoneXR", "ImmigrationCanada", "telus", "Flipping", "FrugalMaleFashionCDN", "travel", "starbucks", "airpods", "personalfinance", "GalaxyS9", "vancouver", "AskReddit", "frugalmalefashion", "UBC", "FedEx", "androidcirclejerk", "AskLosAngeles", "Boots", "privacy", "iPhoneX", "Smartphones", "sennheiser", "AsianBeauty", "Drugs", "samsung", "immigration", "scoliosis", "college", "SneakerDeals", "BitcoinCA", "audiophile", "todayilearned", "funny", "CanSkincare", "askscience", "Bitcoin", "UofT"]}