{"submission_id": "e8583t", "submission_title": "Corner of my office", "submission_url": "/r/Workspaces/comments/e8583t/corner_of_my_office/", "submission_img_url": "https://i.redd.it/c7titwpjgj341.jpg", "submission_author_name": "cryanbranston", "submission_author_id": "cke1u", "submission_author_subreddits": ["ProgrammerHumor", "howardstern", "CafeRacers", "Triumph", "AskMen", "videos", "userexperience", "trippinthroughtime", "popping", "AskReddit", "news", "web_design", "labrador", "Exercise", "CrappyDesign", "RoastMe", "assholedesign", "rarepuppers", "lookatmydog", "ProductPorn", "Ducati", "fitness30plus", "ProductManagement", "webdev", "FromPuppyToDog", "aww", "motorcycles", "legaladvice", "MotoLA", "Showerthoughts", "funny", "Workspaces", "DunderMifflin"]}