{"submission_id": "fnwexz", "submission_title": "Finally got my work station going. Everybody's got time to learn something new!", "submission_url": "/r/workstations/comments/fnwexz/finally_got_my_work_station_going_everybodys_got/", "submission_img_url": "https://i.redd.it/ic8yr24yxio41.jpg", "submission_author_name": "entryleveldeveloper1", "submission_author_id": "5zskrcvd", "submission_author_subreddits": ["node", "cscareerquestions", "javascript", "workstations", "Slack", "googlecloud", "learnprogramming"]}