{"submission_id": "fsf333", "submission_title": "Cleaned up today! :)", "submission_url": "/r/Workspaces/comments/fsf333/cleaned_up_today/", "submission_img_url": "https://i.redd.it/lqihahss21q41.jpg", "submission_author_name": "IrustheVirus", "submission_author_id": "14czok", "submission_author_subreddits": ["MensRights", "localmultiplayergames", "movies", "PoliticalCompassMemes", "n64", "europe", "circlejerk", "explainlikeimfive", "videos", "Jordan_Peterson_Memes", "PoliticalCompass", "stopsmoking", "space", "personalfinance", "AskReddit", "IntellectualDarkWeb", "Blizzard", "mildlyinteresting", "wow", "languagelearning", "germany", "WritingPrompts", "stopdrinking", "berlinsocialclub", "self", "france", "cyberpunkgame", "DnDBehindTheScreen", "de", "DecidingToBeBetter", "television", "WeLiveInaSociety", "ich_iel", "GetMotivatedBuddies", "woweconomy", "gaming", "smallbusiness", "HadesStar", "Art", "newyork", "berlin", "selfimprovement", "tinnitus", "Windows10", "books", "food", "de_IAmA", "riskofrain", "AskNYC", "aww", "JordanPeterson", "Documentaries", "todayilearned", "history", "EarthPorn", "MonkeyIsland", "printSF", "sciencefiction", "pics", "dankmemes", "Gamingcirclejerk", "Showerthoughts", "AskRedditAfterDark", "DnD", "poland", "LifeProTips", "Northgard", "Workspaces", "askscience", "warsaw", "singularity", "stockholm", "getdisciplined"]}