{"submission_id": "fsmbho", "submission_title": "WFH for 8 years. This is my work/gaming station for the past four, pretty much unchanged. This virus doesn't change much to that!", "submission_url": "/r/workstations/comments/fsmbho/wfh_for_8_years_this_is_my_workgaming_station_for/", "submission_img_url": "https://i.redd.it/367xjlqsy2q41.jpg", "submission_author_name": "netcoder", "submission_author_id": "3tfuq", "submission_author_subreddits": ["coding", "weedstocks", "selfhosted", "linuxmasterrace", "ProgrammerHumor", "javascript", "WhitePeopleTwitter", "StockMarket", "brooklynninenine", "SiliconValleyHBO", "relationship_advice", "programming", "ketogains", "PHP", "canada", "Economics", "AskReddit", "nextfuckinglevel", "woooosh", "technews", "climbing", "gifsthatkeepongiving", "geek", "workstations", "AnimalsBeingJerks", "ConvenientCop", "linux", "stocks", "keto", "Billions", "dogswithjobs", "worldnews", "gaming", "youseeingthisshit", "hockey", "politics", "totallynotrobots", "instant_regret", "fo76", "options", "NoStupidQuestions", "instantkarma", "iamatotalpieceofshit", "ABoringDystopia", "Fedora", "uselessredcircle", "gifs", "Ozark", "iamverybadass", "PublicFreakout", "vim", "ChoosingBeggars", "Unexpected", "PHPhelp", "Ubuntu", "pics", "catsareliquid", "science", "technology", "funny", "Supernatural", "OldSchoolCool", "MrRobot", "investing", "nottheonion", "WTF", "homelab"]}