{"submission_id": "ft7899", "submission_title": "My web development and content authoring stand up workstation. WFH for 15+ years, 5 years with this setup.", "submission_url": "/r/workstations/comments/ft7899/my_web_development_and_content_authoring_stand_up/", "submission_img_url": "https://i.redd.it/pkhb82c4c9q41.jpg", "submission_author_name": "NateMonger", "submission_author_id": "4dunwzu5", "submission_author_subreddits": ["drupal", "hoggit", "Cruise", "workstations", "nebelung", "Keto_Food", "PoliticalDiscussion", "cats", "webdev", "Eyebleach", "aww"]}