{"submission_id": "ft90di", "submission_title": "Remote almost 7 years. Just cleaned up the desk and added a plant.", "submission_url": "/r/Workspaces/comments/ft90di/remote_almost_7_years_just_cleaned_up_the_desk/", "submission_img_url": "https://i.redd.it/6bbcvbpgx9q41.jpg", "submission_author_name": "danohart", "submission_author_id": "6316a", "submission_author_subreddits": ["PeoriaIL", "milwaukee", "skateboarding", "cocktails", "bikecommuting", "HIMYM", "BarBattlestations", "weezer", "StLouis", "TheDearHunter", "Queens", "chibike", "Cardinals", "TheStrokes", "IAmA", "dawes", "digitalnomad", "freelance", "Denver", "FixedGearBicycle", "COVIDProjects", "chicagofood", "webdev", "ChicagoList", "RobinHood", "googlehome", "youtube", "Chiskate", "funny", "RiotFest", "snowboarding", "Workspaces", "chicago"]}