{"submission_id": "ggctah", "submission_title": "Built myself a desk slash (very much amateur) home studio. Particularly happy with the retractable piano shelf.", "submission_url": "/r/Workspaces/comments/ggctah/built_myself_a_desk_slash_very_much_amateur_home/", "submission_img_url": "https://i.redd.it/9bg3p98yppx41.jpg", "submission_author_name": "marcx88", "submission_author_id": "dclcz", "submission_author_subreddits": ["movies", "CarPlay", "geocaching", "TechNewsToday", "SelfAwarewolves", "holdmyfeedingtube", "insaneparents", "MurderedByWords", "FUCKYOUINPARTICULAR", "entertainment", "dutch", "BitGrailExchange", "nextfuckinglevel", "tipofmyjoystick", "shittyaskscience", "technews", "news", "nonononoyes", "Prematurecelebration", "dataisbeautiful", "hmmm", "InsanePeopleQuora", "Wellthatsucks", "DartsofFury", "yesyesyesyesno", "DataArt", "watchthingsfly", "maybemaybemaybe", "worldnews", "PoliticalHumor", "bitgrail", "yesyesyesno", "itookapicture", "Whatcouldgowrong", "LateStageCapitalism", "burstcoin", "politics", "SweatyPalms", "memes", "nevertellmetheodds", "therewasanattempt", "apolloapp", "instantkarma", "juxtaposition", "reasoners", "GolfClash", "aww", "gifs", "ChoosingBeggars", "PublicFreakout", "thisismylifenow", "VXJunkies", "Unexpected", "learnpython", "learnprogramming", "pics", "awfuleverything", "Tay_5", "technology", "funny", "nottheonion", "Workspaces", "blackmagicfuckery", "BlackPeopleTwitter", "HolUp", "holdmyfries", "nononono"]}