{"submission_id": "ggo30d", "submission_title": "Still need some more wall decorations but it\u2019s coming together", "submission_url": "/r/battlestations/comments/ggo30d/still_need_some_more_wall_decorations_but_its/", "submission_img_url": "https://i.redd.it/gen19l2n4tx41.jpg", "submission_author_name": "Messoor", "submission_author_id": "136iym", "submission_author_subreddits": ["nintendo", "3DS", "thewalkingdead", "Target", "AskReddit", "pokemon", "battlestations", "headphones", "HeadphoneAdvice", "RandomActsOfGaming", "darksouls3", "gaming", "Borderlands", "sports", "memes", "PUBATTLEGROUNDS", "apolloapp", "Fallout4Builds", "vegas", "apexlegends", "EscapefromTarkov", "guns", "pcmasterrace", "pics", "funny", "pumparum", "Overwatch", "DestinyTheGame", "PS4", "wholesomeanimemes"]}