{"submission_id": "ghox89", "submission_title": "New homebuilt desk for my work from home workstation", "submission_url": "/r/workstations/comments/ghox89/new_homebuilt_desk_for_my_work_from_home/", "submission_img_url": "https://i.redd.it/zk34lpo3f5y41.jpg", "submission_author_name": "ApoplecticAndroid", "submission_author_id": "108ukn", "submission_author_subreddits": ["ATC", "TwoXChromosomes", "interestingasfuck", "freefolk", "UnethicalLifeProTips", "facepalm", "Futurology", "HouseOfCards", "buildapc", "MurderedByWords", "gameofthrones", "beholdthemasterrace", "ImagesOfChina", "AskReddit", "mildlyinteresting", "shittyaskscience", "EnoughTrumpSpam", "YouShouldKnow", "Fuckthealtright", "personalfinance", "namenerds", "nonononoyes", "nba", "ShittyTodayILearned", "workstations", "theydidthemath", "niceguys", "SocialEngineering", "UpliftingNews", "atheism", "asktrp", "seduction", "OutOfTheLoop", "worldnews", "esist", "PoliticalHumor", "olympics", "BetterEveryLoop", "television", "phpstorm", "ShittyLifeProTips", "tifu", "LateStageCapitalism", "OurPresident", "TwoSentenceHorror", "politics", "Art", "shittyaskreddit", "running", "apolloapp", "explainlikeimfive", "composting", "books", "aww", "todayilearned", "buildapcforme", "history", "apple", "TattooDesigns", "asoiaf", "AppleWatch", "Awwducational", "CanadaPolitics", "pics", "BuyItForLife", "science", "Dentistry", "Showerthoughts", "funny", "technology", "Damnthatsinteresting", "LifeProTips", "writing", "Workspaces", "askscience", "Bitcoin", "unpopularopinion", "UrbanHell", "TrumpCriticizesTrump", "listentothis", "golf", "Jokes", "Advice"]}