{"submission_id": "gi4gai", "submission_title": "Just the beginning...", "submission_url": "/r/battlestations/comments/gi4gai/just_the_beginning/", "submission_img_url": "https://i.redd.it/ub0acyasm9y41.jpg", "submission_author_name": "hotbiccies", "submission_author_id": "2kc0htkc", "submission_author_subreddits": ["MMORPG", "MovieStreamingSites", "baldursgate", "blackdesertonline", "Chainlink", "OnePiece", "New_World_MMO", "Allergies", "STD", "2020", "BlackDesertOnlineSEA", "battlestations", "lordoftherings", "GearsOfWar", "ConquerorsBlade"]}