{"submission_id": "gibh2p", "submission_title": "NoOne: \u201chow could you do your master thesis during Covid, using VirtualReality at home?!?\u201d Me and my sister\u2019s room:", "submission_url": "/r/battlestations/comments/gibh2p/noone_how_could_you_do_your_master_thesis_during/", "submission_img_url": "https://i.redd.it/eu6b10jn8cy41.jpg", "submission_author_name": "didigandolfi", "submission_author_id": "2fms2g73", "submission_author_subreddits": ["robotics", "MechanicalKeyboards", "europe", "battlestations", "software"]}