{"submission_id": "gkv3d4", "submission_title": "My new very functional setup.", "submission_url": "/r/battlestations/comments/gkv3d4/my_new_very_functional_setup/", "submission_img_url": "https://i.redd.it/4q33dp35v4z41.jpg", "submission_author_name": "chawful", "submission_author_id": "mh574", "submission_author_subreddits": ["trashy", "summonerschool", "heroesofthestorm", "BeAmazed", "CompetitiveHotS", "Conservative", "Jeep", "GYM", "Dachshund", "personalfinance", "AskReddit", "shower_thoughts", "leagueoflegends", "mildlyinfuriating", "news", "wow", "iamverysmart", "cringepics", "blop", "Monitors", "ThreadGames", "kucoin", "CrappyDesign", "hmmm", "AnthemTheGame", "progresspics", "MouseReview", "battlestations", "FortNiteBR", "RoastMe", "HeadphoneAdvice", "worldnews", "rarepuppers", "netneutrality", "modernwarfare", "Whatcouldgowrong", "gaming", "Cooking", "photoshopbattles", "Fitness", "NoStupidQuestions", "supportlol", "Art", "worldofpvp", "PUBATTLEGROUNDS", "scifi", "Trumpgret", "DestinyPC", "food", "nattyorjuice", "apexlegends", "aww", "zyramains", "blackdesertonline", "pics", "dankmemes", "tattoos", "Showerthoughts", "millionairemakers", "funny", "technology", "Ripple", "Bitcoin", "mildlypenis", "Homebrewing", "golf"]}