{"submission_id": "glkrmx", "submission_title": "Finally finished my new Game / Stream / Recording setup!", "submission_url": "/r/battlestations/comments/glkrmx/finally_finished_my_new_game_stream_recording/", "submission_img_url": "https://i.redd.it/wp28cw0dedz41.jpg", "submission_author_name": "iwifia", "submission_author_id": "au4xn", "submission_author_subreddits": ["SoftwareInc", "movies", "classicwow", "pcgaming", "sysadminresumes", "breakingbad", "smarthome", "Veeam", "diablo3", "TyrionWinsTheThrone", "webhosting", "networking", "CitiesSkylines", "PlayStationPlus", "battlestations", "Diablo", "Android", "Games", "Pennsylvania", "LateStageCapitalism", "gaming", "hockey", "politics", "talesfromtechsupport", "Sprint", "DotA2", "hometheater", "UsenetInvites", "powershelldsc", "sysadminjobs", "Python", "tmobile", "devops", "PS4", "linux_gaming", "SimCity", "AndroidQuestions", "Conservative", "DeathByMillennial", "buildapc", "Alexis_Fawx", "BatwomanTV", "pittsburgh", "FuckYouKaren", "wow", "planetaryannihilation", "chocolatey", "linux", "Terraform", "arrow", "Sysadminhumor", "LateStageSocialism", "ffxiv", "peopleofwalmart", "oneplus", "SurvivingMars", "Steam", "Office365", "RealTimeStrategy", "cloudygamer", "thisisus", "DataHoarder", "tycoon", "technology", "SolusProject", "learnprogramming", "ConspiracyII", "heroesofthestorm", "MMORPG", "ansible", "freefolk", "sophos", "hardwareswap", "Intune", "gameofthrones", "eu4", "truegaming", "Asthma", "steelseries", "announcements", "windowsazure", "PowerShell", "albiononline", "kotor", "swgemu", "ShadowPC", "linuxadmin", "LegendsOfTomorrow", "StarWarsLeaks", "AZURE", "SuggestALaptop", "pcmasterrace", "Restreamio", "amazonecho", "Stellaris", "PCMasterGuide", "lostgeneration", "MatureHardcore", "LivestreamFail", "GuildWars2Builds", "windowsphone", "MensRights", "PleX", "swg", "raspberry_pi", "news", "exchangeserver", "HeroesReborn", "GriefSupport", "Heroes", "gog", "penguins", "dragonage", "EA_NHL", "betterCallSaul", "swtor", "thebutton", "todayilearned", "MarchForNetNeutrality", "buildapcforme", "usefulscripts", "Cloververse", "MDT", "FlashTV", "conspiracy", "MakingaMurderer", "ITCareerQuestions", "sysadmin", "Stargate", "homelab"]}