{"submission_id": "gltnem", "submission_title": "Never satisfied", "submission_url": "/r/battlestations/comments/gltnem/never_satisfied/", "submission_img_url": "https://imgur.com/gallery/qRwuve0", "submission_author_name": "JaxHasHax", "submission_author_id": "12dml8", "submission_author_subreddits": ["trees", "HumansBeingBros", "videos", "CannabisExtracts", "teenagers", "FortniteCompetitive", "AskReddit", "mildlyinteresting", "thanosdidnothingwrong", "AverageBattlestations", "FortNiteBR", "surfing", "battlestations", "GlobalOffensive", "shamelessplug", "Psychonaut", "Eyebleach", "gaming", "shrooms", "u_BlueGleepstone", "Vaping", "gifs", "aww", "whatisthisthing", "pics", "funny", "xboxone"]}