{"submission_id": "gmlvgy", "submission_title": "Just moved in!", "submission_url": "/r/battlestations/comments/gmlvgy/just_moved_in/", "submission_img_url": "https://i.redd.it/l89lkmmf6pz41.jpg", "submission_author_name": "Cornbre4d", "submission_author_id": "iffzr", "submission_author_subreddits": ["ClashOfClans", "FORTnITE", "Nioh", "movies", "verizon", "pcgaming", "remnantgame", "NatureIsFuckingLit", "DiscJam", "freefolk", "OverwatchUniversity", "playstation", "thewalkingdead", "reddeadredemption", "DestinyFashion", "forhonor", "Fireteams", "dbz", "FortniteCompetitive", "gameofthrones", "MECoOp", "horizon", "leagueoflegends", "destiny2", "truegaming", "fakealbumcovers", "Monitors", "absolver", "hiphopheads", "masseffect", "AnthemTheGame", "MonsterHunter", "battlestations", "FortNiteBR", "OWConsole", "Coronavirus", "modernwarfare", "MortalKombat", "titanfall", "nvidia", "LateStageCapitalism", "gaming", "VALORANT", "darksouls3", "MonsterHunterWorld", "FortniteBattleRoyale", "politics", "PS4Pro", "thedivision", "Fitness", "BattleRite", "westworld", "BikiniBottomTwitter", "Twitch", "Competitiveoverwatch", "pyre", "apexlegends", "dragonballfighterz", "Blackops4", "CruciblePlaybook", "borderlands3", "pcmasterrace", "apple", "Borderlands", "paragon", "Sneakers", "bloodborne", "ARK", "funny", "Overwatch", "DestinyTheGame", "PS4", "xboxone", "GearsOfWar", "nba"]}