{"submission_id": "gmne5d", "submission_title": "Anyone here waiting for #TheLastofus2 ?", "submission_url": "/r/battlestations/comments/gmne5d/anyone_here_waiting_for_thelastofus2/", "submission_img_url": "https://i.redd.it/h9aknw82rpz41.jpg", "submission_author_name": "aguyong", "submission_author_id": "4h1q5ba0", "submission_author_subreddits": ["razerbladestealth", "Nanoleaf", "Note10Wallpaper", "BMW", "AirpodsPro", "GodofWar", "FinalFantasy", "Note10FanBase", "battlestations", "razer", "secretlab", "thelastofus", "AnimeFigures", "dbrand"]}