{"submission_id": "go47hh", "submission_title": "I\u2019m the guy with the setup under my bed, like 500 of you said clean your desktop, ya happy now?", "submission_url": "/r/battlestations/comments/go47hh/im_the_guy_with_the_setup_under_my_bed_like_500/", "submission_img_url": "https://i.redd.it/2vg5rgkid6051.jpg", "submission_author_name": "JustJonYT", "submission_author_id": "31w4oxq2", "submission_author_subreddits": ["teenagers", "PCPorn", "pcmasterrace", "blursedimages", "CoronavirusUS", "Jazza", "Weirdlyhot", "Minecraft", "AskReddit", "MinecraftServer", "sports", "battlestations", "mcservers", "youngpeopleyoutube", "WillNE", "Symbology", "rarepuppers", "MemeFormats", "HydroDip", "antivaccine", "wheredoesthisgo", "gameglitches", "seemslegit", "accidentalswastika", "Boomerhumour", "technicallythetruth", "iamatotalpieceofshit", "GiveitTomeNow", "memes", "gifs", "Wellthatsucks", "interestingasfuck", "admincraft", "DetailCraft", "boomerhentai", "AccidentalRacism", "oddlysatisfying", "Music", "ThatLookedExpensive", "Goodboomerhumour", "JerkOffToCelebs", "BoomerYiff", "skamtebord", "nextfuckinglevel", "suddenlysexoffender", "dontdeadopeninside", "comedyheaven", "JustJon", "HermitCraft", "terriblefacebookmemes"]}