{"submission_id": "go8l2e", "submission_title": "This is my happy place (:", "submission_url": "/r/battlestations/comments/go8l2e/this_is_my_happy_place/", "submission_img_url": "https://imgur.com/gallery/edaamA0", "submission_author_name": "jacksonredditforonce", "submission_author_id": "5dwsaa0j", "submission_author_subreddits": ["UnexpectedLetterkenny", "ShadowPC", "battlestations", "macsetups", "MechanicalKeyboards", "gamingsetups", "mechmarket", "pcmasterrace", "Hulu", "wholesomememes", "weed", "modernwarfare", "projectsession", "Random_Acts_Of_Amazon", "mechanicalheadpens", "PewdiepieSubmissions", "AverageBattlestations", "photoshopbattles", "AskReddit", "CozyPlaces", "wallpaper", "CustomKeyboards", "MechGroupBuys", "gaming", "hardwareswap", "buildapc", "interestingasfuck", "worldnews", "ShouldIbuythisgame", "headphones", "knives", "csgo", "Battletops", "steam_giveaway", "PictureGame", "malelivingspace", "textfriends", "worldpolitics", "olkb", "RandomKindness", "Art", "keyboards", "shittybattlestations", "ThatPeelingFeeling"]}