{"submission_id": "goqz0r", "submission_title": "Ready for online classes!", "submission_url": "/r/battlestations/comments/goqz0r/ready_for_online_classes/", "submission_img_url": "https://i.redd.it/ijttrun4kd051.jpg", "submission_author_name": "Vogako", "submission_author_id": "144coe", "submission_author_subreddits": ["fasting", "AskReddit", "EarthPorn", "EDC", "homelab", "CryptoCurrency", "battlestations", "skiing", "loseit", "Warframe", "food", "pcmasterrace", "homelabsales", "aww", "personalfinance", "MTB", "pics", "EngineeringStudents", "stratisplatform", "PersonalFinanceCanada", "MechanicAdvice", "FixMyPrint", "matt", "flowers", "MechanicalKeyboards", "Surface", "3Dprinting", "wallpaper", "gpumining", "Showerthoughts", "nvidia", "JDM_WAAAT", "flatearth", "inthenews", "watercooling", "IWantOut", "Ultralight", "askscience", "thenetherlands", "KerbalSpaceProgram", "PrintrBot", "Overwatch_Memes", "Amd", "photoshopbattles", "mildly_penis", "knives", "engineeringmemes", "terriblefacebookmemes", "Cheese", "lbry", "dankmemes", "relationship_advice", "memes", "SAIT", "UBC", "OldSchoolCool", "AncestryDNA", "worldnews", "sysadmin", "Futurology", "funny", "canada", "Tinder", "NiceHash", "explainlikeimfive", "Calgary", "surfaceprox", "history", "engineering", "gifs", "todayilearned", "youtube", "mildlyinteresting"]}