{"submission_id": "goylb1", "submission_title": "Just finished my first build, what do you guys think!", "submission_url": "/r/battlestations/comments/goylb1/just_finished_my_first_build_what_do_you_guys/", "submission_img_url": "https://i.redd.it/4dbyr32nxf051.jpg", "submission_author_name": "a_vaiasuso_jr", "submission_author_id": "2vufw4hy", "submission_author_subreddits": ["Target", "Anthony", "vegas", "dank_meme", "RectalStickers", "battlestations", "unexpectedcommunism", "dankmemes", "starbucks", "AirForce", "CasualConversation", "RoastMe", "PewdiepieSubmissions", "Logic_301", "apexlegends", "AskReddit"]}