{"submission_id": "gpegwo", "submission_title": "Waifu Battlestation 2020", "submission_url": "/r/battlestations/comments/gpegwo/waifu_battlestation_2020/", "submission_img_url": "https://i.redd.it/08li03tugl051.jpg", "submission_author_name": "jprovido", "submission_author_id": "9xuo5", "submission_author_subreddits": ["Amd", "pcmasterrace", "razerphone", "battlestations", "oculus", "intel", "gamingpc", "AVexchange", "iphone", "audiophile", "nintendo", "headphones", "hardwareswap", "playstation", "aww", "news", "pics", "movies", "gifs", "worldnews", "space", "OldSchoolCool", "anime", "personalfinance", "nba", "DotA2", "AskReddit", "gaming"]}