{"submission_id": "gqgeqb", "submission_title": "My quarantine WFH/SFH setup", "submission_url": "/r/battlestations/comments/gqgeqb/my_quarantine_wfhsfh_setup/", "submission_img_url": "https://i.redd.it/i82alnb1gy051.jpg", "submission_author_name": "Neodman", "submission_author_id": "10pklq", "submission_author_subreddits": ["tattoos", "starcitizen", "battlestations", "masseffect", "AnthemTheGame", "freefolk", "swtor", "MortalKombat", "space", "SWGalaxyOfHeroes", "rocketry", "AskReddit", "PrequelMemes", "Drexel", "aSongOfMemesAndRage", "AerospaceEngineering", "MURICA", "aerospace", "EliteDangerous", "spaceflight", "ROTC", "MECoOp", "Fashionlancers", "dragonage", "AQ3D", "Zoomies", "SpaceXMasterrace"]}