<annotation>
	<folder>Group 2</folder>
	<filename>24_8bou2j.jpg</filename>
	<path>/home/fronchettl/Documents/temp/img/Group 2/24_8bou2j.jpg</path>
	<source>
		<database>Unknown</database>
	</source>
	<size>
		<width>3024</width>
		<height>4032</height>
		<depth>3</depth>
	</size>
	<segmented>0</segmented>
	<object>
		<name>Monitor (Landscape)</name>
		<pose>Unspecified</pose>
		<truncated>0</truncated>
		<difficult>0</difficult>
		<bndbox>
			<xmin>1572</xmin>
			<ymin>994</ymin>
			<xmax>2478</xmax>
			<ymax>1809</ymax>
		</bndbox>
	</object>
	<object>
		<name>Monitor (Landscape)</name>
		<pose>Unspecified</pose>
		<truncated>0</truncated>
		<difficult>0</difficult>
		<bndbox>
			<xmin>747</xmin>
			<ymin>1050</ymin>
			<xmax>1660</xmax>
			<ymax>2028</ymax>
		</bndbox>
	</object>
	<object>
		<name>Laptop (Linux)</name>
		<pose>Unspecified</pose>
		<truncated>1</truncated>
		<difficult>0</difficult>
		<bndbox>
			<xmin>1</xmin>
			<ymin>2284</ymin>
			<xmax>763</xmax>
			<ymax>3086</ymax>
		</bndbox>
	</object>
	<object>
		<name>Keyboard (Generic)</name>
		<pose>Unspecified</pose>
		<truncated>0</truncated>
		<difficult>0</difficult>
		<bndbox>
			<xmin>1547</xmin>
			<ymin>1928</ymin>
			<xmax>2475</xmax>
			<ymax>2488</ymax>
		</bndbox>
	</object>
	<object>
		<name>Mouse (Generic)</name>
		<pose>Unspecified</pose>
		<truncated>0</truncated>
		<difficult>0</difficult>
		<bndbox>
			<xmin>2375</xmin>
			<ymin>1872</ymin>
			<xmax>2635</xmax>
			<ymax>2041</ymax>
		</bndbox>
	</object>
	<object>
		<name>Headphones</name>
		<pose>Unspecified</pose>
		<truncated>0</truncated>
		<difficult>0</difficult>
		<bndbox>
			<xmin>691</xmin>
			<ymin>1663</ymin>
			<xmax>1047</xmax>
			<ymax>2344</ymax>
		</bndbox>
	</object>
	<object>
		<name>Chair (Generic)</name>
		<pose>Unspecified</pose>
		<truncated>1</truncated>
		<difficult>0</difficult>
		<bndbox>
			<xmin>1815</xmin>
			<ymin>2560</ymin>
			<xmax>3024</xmax>
			<ymax>4012</ymax>
		</bndbox>
	</object>
	<object>
		<name>Desk (Generic)</name>
		<pose>Unspecified</pose>
		<truncated>1</truncated>
		<difficult>0</difficult>
		<bndbox>
			<xmin>32</xmin>
			<ymin>1545</ymin>
			<xmax>3024</xmax>
			<ymax>3906</ymax>
		</bndbox>
	</object>
	<object>
		<name>Decoration (Picture)</name>
		<pose>Unspecified</pose>
		<truncated>1</truncated>
		<difficult>0</difficult>
		<bndbox>
			<xmin>91</xmin>
			<ymin>1</ymin>
			<xmax>1632</xmax>
			<ymax>696</ymax>
		</bndbox>
	</object>
</annotation>
