<annotation>
	<folder>Group 2 (IMG)</folder>
	<filename>56_fzjlzx.jpg</filename>
	<path>C:\Users\krugdl\Documents\Group 2\Group 2 (IMG)\56_fzjlzx.jpg</path>
	<source>
		<database>Unknown</database>
	</source>
	<size>
		<width>8420</width>
		<height>3830</height>
		<depth>3</depth>
	</size>
	<segmented>0</segmented>
	<object>
		<name>Laptop (OSX)</name>
		<pose>Unspecified</pose>
		<truncated>0</truncated>
		<difficult>0</difficult>
		<bndbox>
			<xmin>2257</xmin>
			<ymin>1452</ymin>
			<xmax>2891</xmax>
			<ymax>1928</ymax>
		</bndbox>
	</object>
	<object>
		<name>Laptop (OSX)</name>
		<pose>Unspecified</pose>
		<truncated>0</truncated>
		<difficult>0</difficult>
		<bndbox>
			<xmin>3156</xmin>
			<ymin>1412</ymin>
			<xmax>3652</xmax>
			<ymax>1804</ymax>
		</bndbox>
	</object>
	<object>
		<name>Desk (Generic)</name>
		<pose>Unspecified</pose>
		<truncated>0</truncated>
		<difficult>0</difficult>
		<bndbox>
			<xmin>1886</xmin>
			<ymin>1485</ymin>
			<xmax>4000</xmax>
			<ymax>3005</ymax>
		</bndbox>
	</object>
	<object>
		<name>Chair (Generic)</name>
		<pose>Unspecified</pose>
		<truncated>0</truncated>
		<difficult>0</difficult>
		<bndbox>
			<xmin>2651</xmin>
			<ymin>1608</ymin>
			<xmax>3557</xmax>
			<ymax>3068</ymax>
		</bndbox>
	</object>
	<object>
		<name>Lamp (Floor)</name>
		<pose>Unspecified</pose>
		<truncated>0</truncated>
		<difficult>0</difficult>
		<bndbox>
			<xmin>3774</xmin>
			<ymin>488</ymin>
			<xmax>4089</xmax>
			<ymax>2405</ymax>
		</bndbox>
	</object>
	<object>
		<name>Decoration (Plant)</name>
		<pose>Unspecified</pose>
		<truncated>0</truncated>
		<difficult>0</difficult>
		<bndbox>
			<xmin>6166</xmin>
			<ymin>805</ymin>
			<xmax>7306</xmax>
			<ymax>3098</ymax>
		</bndbox>
	</object>
	<object>
		<name>Decoration (Plant)</name>
		<pose>Unspecified</pose>
		<truncated>0</truncated>
		<difficult>0</difficult>
		<bndbox>
			<xmin>7086</xmin>
			<ymin>1791</ymin>
			<xmax>7579</xmax>
			<ymax>2305</ymax>
		</bndbox>
	</object>
	<object>
		<name>Decoration (Plant)</name>
		<pose>Unspecified</pose>
		<truncated>0</truncated>
		<difficult>0</difficult>
		<bndbox>
			<xmin>7399</xmin>
			<ymin>2411</ymin>
			<xmax>7953</xmax>
			<ymax>3085</ymax>
		</bndbox>
	</object>
	<object>
		<name>Decoration (Picture)</name>
		<pose>Unspecified</pose>
		<truncated>1</truncated>
		<difficult>0</difficult>
		<bndbox>
			<xmin>1173</xmin>
			<ymin>1</ymin>
			<xmax>2063</xmax>
			<ymax>1138</ymax>
		</bndbox>
	</object>
	<object>
		<name>Decoration (Picture)</name>
		<pose>Unspecified</pose>
		<truncated>1</truncated>
		<difficult>0</difficult>
		<bndbox>
			<xmin>3207</xmin>
			<ymin>1</ymin>
			<xmax>3819</xmax>
			<ymax>1211</ymax>
		</bndbox>
	</object>
	<object>
		<name>Decoration (Picture)</name>
		<pose>Unspecified</pose>
		<truncated>1</truncated>
		<difficult>0</difficult>
		<bndbox>
			<xmin>3979</xmin>
			<ymin>1</ymin>
			<xmax>4653</xmax>
			<ymax>1411</ymax>
		</bndbox>
	</object>
	<object>
		<name>Decoration (Picture)</name>
		<pose>Unspecified</pose>
		<truncated>1</truncated>
		<difficult>0</difficult>
		<bndbox>
			<xmin>6126</xmin>
			<ymin>1</ymin>
			<xmax>7085</xmax>
			<ymax>1478</ymax>
		</bndbox>
	</object>
	<object>
		<name>Decoration (Picture)</name>
		<pose>Unspecified</pose>
		<truncated>1</truncated>
		<difficult>0</difficult>
		<bndbox>
			<xmin>7353</xmin>
			<ymin>1</ymin>
			<xmax>8393</xmax>
			<ymax>1331</ymax>
		</bndbox>
	</object>
</annotation>
