<annotation>
	<folder>Group 0</folder>
	<filename>38_7gdjm6.jpg</filename>
	<path>/home/fronchettl/Documents/temp/img/Group 0/38_7gdjm6.jpg</path>
	<source>
		<database>Unknown</database>
	</source>
	<size>
		<width>2048</width>
		<height>1536</height>
		<depth>3</depth>
	</size>
	<segmented>0</segmented>
	<object>
		<name>Monitor (Landscape)</name>
		<pose>Unspecified</pose>
		<truncated>0</truncated>
		<difficult>0</difficult>
		<bndbox>
			<xmin>274</xmin>
			<ymin>680</ymin>
			<xmax>822</xmax>
			<ymax>998</ymax>
		</bndbox>
	</object>
	<object>
		<name>Monitor (Landscape)</name>
		<pose>Unspecified</pose>
		<truncated>0</truncated>
		<difficult>0</difficult>
		<bndbox>
			<xmin>825</xmin>
			<ymin>677</ymin>
			<xmax>1257</xmax>
			<ymax>951</ymax>
		</bndbox>
	</object>
	<object>
		<name>Monitor (Landscape)</name>
		<pose>Unspecified</pose>
		<truncated>0</truncated>
		<difficult>0</difficult>
		<bndbox>
			<xmin>227</xmin>
			<ymin>1053</ymin>
			<xmax>530</xmax>
			<ymax>1346</ymax>
		</bndbox>
	</object>
	<object>
		<name>Monitor (Landscape)</name>
		<pose>Unspecified</pose>
		<truncated>0</truncated>
		<difficult>0</difficult>
		<bndbox>
			<xmin>528</xmin>
			<ymin>1024</ymin>
			<xmax>846</xmax>
			<ymax>1273</ymax>
		</bndbox>
	</object>
	<object>
		<name>Monitor (Landscape)</name>
		<pose>Unspecified</pose>
		<truncated>0</truncated>
		<difficult>0</difficult>
		<bndbox>
			<xmin>1610</xmin>
			<ymin>1041</ymin>
			<xmax>1951</xmax>
			<ymax>1346</ymax>
		</bndbox>
	</object>
	<object>
		<name>Monitor (iMac)</name>
		<pose>Unspecified</pose>
		<truncated>0</truncated>
		<difficult>0</difficult>
		<bndbox>
			<xmin>897</xmin>
			<ymin>991</ymin>
			<xmax>1181</xmax>
			<ymax>1241</ymax>
		</bndbox>
	</object>
	<object>
		<name>Monitor (iMac)</name>
		<pose>Unspecified</pose>
		<truncated>0</truncated>
		<difficult>0</difficult>
		<bndbox>
			<xmin>1324</xmin>
			<ymin>1007</ymin>
			<xmax>1538</xmax>
			<ymax>1290</ymax>
		</bndbox>
	</object>
	<object>
		<name>Telephone</name>
		<pose>Unspecified</pose>
		<truncated>0</truncated>
		<difficult>0</difficult>
		<bndbox>
			<xmin>1237</xmin>
			<ymin>1080</ymin>
			<xmax>1368</xmax>
			<ymax>1220</ymax>
		</bndbox>
	</object>
	<object>
		<name>Keyboard (Generic)</name>
		<pose>Unspecified</pose>
		<truncated>0</truncated>
		<difficult>0</difficult>
		<bndbox>
			<xmin>497</xmin>
			<ymin>1273</ymin>
			<xmax>751</xmax>
			<ymax>1356</ymax>
		</bndbox>
	</object>
	<object>
		<name>Keyboard (Generic)</name>
		<pose>Unspecified</pose>
		<truncated>0</truncated>
		<difficult>0</difficult>
		<bndbox>
			<xmin>938</xmin>
			<ymin>1243</ymin>
			<xmax>1084</xmax>
			<ymax>1285</ymax>
		</bndbox>
	</object>
	<object>
		<name>Keyboard (Generic)</name>
		<pose>Unspecified</pose>
		<truncated>0</truncated>
		<difficult>0</difficult>
		<bndbox>
			<xmin>1288</xmin>
			<ymin>1259</ymin>
			<xmax>1420</xmax>
			<ymax>1313</ymax>
		</bndbox>
	</object>
	<object>
		<name>Keyboard (Generic)</name>
		<pose>Unspecified</pose>
		<truncated>0</truncated>
		<difficult>0</difficult>
		<bndbox>
			<xmin>1501</xmin>
			<ymin>1362</ymin>
			<xmax>1753</xmax>
			<ymax>1472</ymax>
		</bndbox>
	</object>
	<object>
		<name>Laptop (OSX)</name>
		<pose>Unspecified</pose>
		<truncated>0</truncated>
		<difficult>0</difficult>
		<bndbox>
			<xmin>1599</xmin>
			<ymin>1332</ymin>
			<xmax>1891</xmax>
			<ymax>1457</ymax>
		</bndbox>
	</object>
	<object>
		<name>Mouse (Magic Trackpad)</name>
		<pose>Unspecified</pose>
		<truncated>0</truncated>
		<difficult>0</difficult>
		<bndbox>
			<xmin>751</xmin>
			<ymin>1282</ymin>
			<xmax>842</xmax>
			<ymax>1316</ymax>
		</bndbox>
	</object>
	<object>
		<name>Mouse (Magic Trackpad)</name>
		<pose>Unspecified</pose>
		<truncated>0</truncated>
		<difficult>0</difficult>
		<bndbox>
			<xmin>1072</xmin>
			<ymin>1231</ymin>
			<xmax>1164</xmax>
			<ymax>1261</ymax>
		</bndbox>
	</object>
	<object>
		<name>Mouse (Magic Trackpad)</name>
		<pose>Unspecified</pose>
		<truncated>1</truncated>
		<difficult>0</difficult>
		<bndbox>
			<xmin>1691</xmin>
			<ymin>1460</ymin>
			<xmax>1862</xmax>
			<ymax>1536</ymax>
		</bndbox>
	</object>
	<object>
		<name>Mouse (Generic)</name>
		<pose>Unspecified</pose>
		<truncated>0</truncated>
		<difficult>0</difficult>
		<bndbox>
			<xmin>1393</xmin>
			<ymin>1302</ymin>
			<xmax>1442</xmax>
			<ymax>1332</ymax>
		</bndbox>
	</object>
	<object>
		<name>Tablet (Generic)</name>
		<pose>Unspecified</pose>
		<truncated>0</truncated>
		<difficult>0</difficult>
		<bndbox>
			<xmin>349</xmin>
			<ymin>1307</ymin>
			<xmax>504</xmax>
			<ymax>1384</ymax>
		</bndbox>
	</object>
	<object>
		<name>Tablet (iPad)</name>
		<pose>Unspecified</pose>
		<truncated>0</truncated>
		<difficult>0</difficult>
		<bndbox>
			<xmin>1251</xmin>
			<ymin>1221</ymin>
			<xmax>1395</xmax>
			<ymax>1266</ymax>
		</bndbox>
	</object>
	<object>
		<name>Desk (Generic)</name>
		<pose>Unspecified</pose>
		<truncated>1</truncated>
		<difficult>0</difficult>
		<bndbox>
			<xmin>206</xmin>
			<ymin>1198</ymin>
			<xmax>2048</xmax>
			<ymax>1536</ymax>
		</bndbox>
	</object>
	<object>
		<name>Water Bottle</name>
		<pose>Unspecified</pose>
		<truncated>1</truncated>
		<difficult>0</difficult>
		<bndbox>
			<xmin>1891</xmin>
			<ymin>1339</ymin>
			<xmax>1959</xmax>
			<ymax>1536</ymax>
		</bndbox>
	</object>
	<object>
		<name>Mug</name>
		<pose>Unspecified</pose>
		<truncated>1</truncated>
		<difficult>0</difficult>
		<bndbox>
			<xmin>1928</xmin>
			<ymin>1464</ymin>
			<xmax>2022</xmax>
			<ymax>1536</ymax>
		</bndbox>
	</object>
	<object>
		<name>Mousepad (Generic)</name>
		<pose>Unspecified</pose>
		<truncated>0</truncated>
		<difficult>0</difficult>
		<bndbox>
			<xmin>845</xmin>
			<ymin>1266</ymin>
			<xmax>965</xmax>
			<ymax>1312</ymax>
		</bndbox>
	</object>
</annotation>
